{
  "project_info": {
    "project_number": "187121653560",
    "firebase_url": "https://sensordetec.firebaseio.com",
    "project_id": "sensordetec",
    "storage_bucket": "sensordetec.appspot.com"
  },
  "client": [
    {
      "client_info": {
        "mobilesdk_app_id": "1:187121653560:android:fab293031839c3ef",
        "android_client_info": {
          "package_name": "official.com.sensordetector"
        }
      },
      "oauth_client": [
        {
          "client_id": "187121653560-5ti0dlf7rqdrmoi44uu0hlda2elell25.apps.googleusercontent.com",
          "client_type": 1,
          "android_info": {
            "package_name": "official.com.sensordetector",
            "certificate_hash": "786bba8bc29f83935ccce66508fdc9bf2bcd7f91"
          }
        },
        {
          "client_id": "187121653560-82lsukkbmp4r6crg9bub5e2c3cmac8d7.apps.googleusercontent.com",
          "client_type": 3
        }
      ],
      "api_key": [
        {
          "current_key": "AIzaSyB3RMnTayvJtlV8VAKF-o3HkvxeVHgy0EE"
        }
      ],
      "services": {
        "appinvite_service": {
          "other_platform_oauth_client": [
            {
              "client_id": "187121653560-82lsukkbmp4r6crg9bub5e2c3cmac8d7.apps.googleusercontent.com",
              "client_type": 3
            }
          ]
        }
      }
    }
  ],
  "configuration_version": "1"
}